{
	"easycom": {
		"^u-(.*)": "@/uview-ui/components/u-$1/u-$1.vue"
	},
	"pages": [ //pages数组中第一项表示应用启动页，参考：https://uniapp.dcloud.io/collocation/pages
		{
			"path": "pages/index/index",
			"style": {
				"navigationBarTitleText": "萌芽工作室",
				"navigationStyle": "custom"
			}
		},
        {
            "path" : "pages/about/about",
            "style" :                                                                                    
            {
                "navigationBarTitleText": "",
                "enablePullDownRefresh": false,
				"navigationBarBackgroundColor":"#3ad6b1"
            }
            
        },
		// 大赛习题
		{
		    "path" : "pages/quiz/practice/index",
		    "style" :                                                                                    
		    {
		        "navigationBarTitleText": "练习模式",
		        "enablePullDownRefresh": false,
				"navigationBarBackgroundColor":"#FDFAED"
		    }
		},
		{
		    "path" : "pages/quiz/practice/practice",
		    "style" :                                                                                    
		    {
		        "navigationBarTitleText": "练习模式",
		        "enablePullDownRefresh": false,
				"navigationBarBackgroundColor":"#fff"
				// "navigationStyle":"custom"
		    }
		},
		{
		    "path" : "pages/quiz/practice/score",
		    "style" :                                                                                    
		    {
		        "navigationBarTitleText": "得分",
		        "enablePullDownRefresh": false,
				"navigationBarBackgroundColor":"#3ad6b1"
		    }
		},
		// 技术博客
		{
		    "path" : "pages/blog/index",
		    "style" :                                                                                    
		    {
				"navigationBarTitleText": "博客",
				"enablePullDownRefresh": false
		    }
		},
		{
		    "path" : "pages/blog/blogDetails",
		    "style" :                                                                                    
		    {
		        "navigationBarTitleText": "博客详情",
		        "enablePullDownRefresh": false
		    }
		},
		// 近期动态
		{
		    "path" : "pages/information/index",
		    "style" :                                                                                    
		    {
				"navigationBarTitleText": "动态",
				"enablePullDownRefresh": false
		    }
		},
		{
		    "path" : "pages/information/detail",
		    "style" :                                                                                    
		    {
				"navigationBarTitleText": "动态详情",
				"enablePullDownRefresh": false
		    }
		}
		//大赛习题
        ,{
            "path" : "pages/quiz/index",
            "style" :                                                                                    
            {
                "navigationBarTitleText": "",
                "enablePullDownRefresh": false,
				"navigationBarBackgroundColor":"#3ad6b1"
            }
            
        }
        ,{
            "path" : "pages/quiz/wrong/index",
            "style" :                                                                                    
            {
                "navigationBarTitleText": "我的错题",
                "enablePullDownRefresh": false,
				"navigationBarBackgroundColor":"#FDFAED"
            }
            
        }
        ,{
            "path" : "pages/quiz/wrong/manage",
            "style" :                                                                                    
            {
                "navigationBarTitleText": "",
                "enablePullDownRefresh": false
            }
            
        }
		,{
		    "path" : "pages/quiz/wrong/practice",
		    "style" :                                                                                    
		    {
		        "navigationBarTitleText": "",
		        "enablePullDownRefresh": false
		    }
		    
		}
        ,{
            "path" : "pages/achievement/index",
            "style" :                                                                                    
            {
                "navigationBarTitleText": "",
                "enablePullDownRefresh": false
            }
            
        }
    ],
	"globalStyle": {
		"navigationBarTextStyle": "black",
		"navigationBarTitleText": "Seed Studio",
		"navigationBarBackgroundColor": "#F8F8F8",
		"backgroundColor": "#F8F8F8"
	}
}
